{
    "status": {
        "timestamp": "2025-09-21T21:03:22.641Z",
        "error_code": 0,
        "error_message": null,
        "elapsed": 25,
        "credit_count": 1,
        "notice": null
    },
    "data": {
        "active_cryptocurrencies": 9526,
        "total_cryptocurrencies": 36105,
        "active_market_pairs": 111453,
        "active_exchanges": 851,
        "total_exchanges": 11142,
        "eth_dominance": 13.419163822623,
        "btc_dominance": 57.077424092471,
        "eth_dominance_yesterday": 13.4075218,
        "btc_dominance_yesterday": 57.11788592,
        "eth_dominance_24h_percentage_change": 0.011642022623,
        "btc_dominance_24h_percentage_change": -0.040461827529,
        "defi_volume_24h": 24273811770.488426,
        "defi_volume_24h_reported": 85460515864.58817,
        "defi_market_cap": 128727198171.66275,
        "defi_24h_percentage_change": 42.248118026083,
        "stablecoin_volume_24h": 96917324065.30774,
        "stablecoin_volume_24h_reported": 406318758445.1406,
        "stablecoin_market_cap": 273085410009.6326,
        "stablecoin_24h_percentage_change": 5.73704573458,
        "derivatives_volume_24h": 1078126854265.107,
        "derivatives_volume_24h_reported": 1078126854265.107,
        "derivatives_24h_percentage_change": 4.770243195993,
        "total_crypto_dex_currencies": 21643186,
        "today_incremental_crypto_number": 5,
        "past_24h_incremental_crypto_number": 49574,
        "past_7d_incremental_crypto_number": 358096,
        "past_30d_incremental_crypto_number": 1701458,
        "today_change_percent": 0.016072305597,
        "tracked_yearly_number": {
            "maxIncrementalNumber": 184087,
            "minIncrementalNumber": 3478,
            "maxIncrementalDate": "2025-04-17T00:00:00.000Z",
            "minIncrementalDate": "2025-09-21T00:00:00.000Z"
        },
        "quote": {
            "USD": {
                "total_market_cap": 4027774615226.6514,
                "total_volume_24h": 103024717417.35,
                "total_volume_24h_reported": 416614374037.54,
                "altcoin_volume_24h": 80491057153.17998,
                "altcoin_volume_24h_reported": 342345116477.682,
                "altcoin_market_cap": 1728824616604.842,
                "defi_volume_24h": 24273811770.488426,
                "defi_volume_24h_reported": 85460515864.58817,
                "defi_24h_percentage_change": 42.248118026083,
                "defi_market_cap": 128727198171.66275,
                "stablecoin_volume_24h": 96917324065.30774,
                "stablecoin_volume_24h_reported": 406318758445.1406,
                "stablecoin_24h_percentage_change": 5.73704573458,
                "stablecoin_market_cap": 273085410009.6326,
                "derivatives_volume_24h": 1078126854265.107,
                "derivatives_volume_24h_reported": 1078126854265.107,
                "derivatives_24h_percentage_change": 4.770243195993,
                "total_market_cap_yesterday": 4039976030373.8257,
                "total_volume_24h_yesterday": 95797467825.1,
                "total_market_cap_yesterday_percentage_change": -0.3020170183050652,
                "total_volume_24h_yesterday_percentage_change": 7.544301280953476,
                "last_updated": "2025-09-21T21:01:59.999Z"
            }
        },
        "last_updated": "2025-09-21T21:01:59.999Z"
    }
}