{
    "status": {
        "timestamp": "2024-07-04T11:03:47.898Z",
        "error_code": 0,
        "error_message": null,
        "elapsed": 14,
        "credit_count": 1,
        "notice": null
    },
    "data": {
        "active_cryptocurrencies": 10013,
        "total_cryptocurrencies": 30502,
        "active_market_pairs": 83180,
        "active_exchanges": 787,
        "total_exchanges": 8889,
        "eth_dominance": 17.804223556934,
        "btc_dominance": 53.394920189919,
        "eth_dominance_yesterday": 17.80706043,
        "btc_dominance_yesterday": 53.23060747,
        "eth_dominance_24h_percentage_change": -0.002836873066,
        "btc_dominance_24h_percentage_change": 0.164312719919,
        "defi_volume_24h": 7152252175.037789,
        "defi_volume_24h_reported": 33046666504.113605,
        "defi_market_cap": 67417193073.66446,
        "defi_24h_percentage_change": 67.990940636625,
        "stablecoin_volume_24h": 85378788186.09566,
        "stablecoin_volume_24h_reported": 447470827346.4177,
        "stablecoin_market_cap": 154745900023.674,
        "stablecoin_24h_percentage_change": 48.751328750203,
        "derivatives_volume_24h": 709401619013.9893,
        "derivatives_volume_24h_reported": 712643216472.7592,
        "derivatives_24h_percentage_change": 27.279498752541,
        "quote": {
            "USD": {
                "total_market_cap": 2138241016540.6736,
                "total_volume_24h": 91167853057.05,
                "total_volume_24h_reported": 463961023239.84,
                "altcoin_volume_24h": 53513780367.97522,
                "altcoin_volume_24h_reported": 267197894362.11768,
                "altcoin_market_cap": 996528932290.6643,
                "defi_volume_24h": 7152252175.037789,
                "defi_volume_24h_reported": 33046666504.113605,
                "defi_24h_percentage_change": 67.990940636625,
                "defi_market_cap": 67417193073.66446,
                "stablecoin_volume_24h": 85378788186.09566,
                "stablecoin_volume_24h_reported": 447470827346.4177,
                "stablecoin_24h_percentage_change": 48.751328750203,
                "stablecoin_market_cap": 154745900023.674,
                "derivatives_volume_24h": 709401619013.9893,
                "derivatives_volume_24h_reported": 712643216472.7592,
                "derivatives_24h_percentage_change": 27.279498752541,
                "total_market_cap_yesterday": 2230634124714.379,
                "total_volume_24h_yesterday": 61600645375.29,
                "total_market_cap_yesterday_percentage_change": -4.142010881570997,
                "total_volume_24h_yesterday_percentage_change": 47.998210897998746,
                "last_updated": "2024-07-04T11:01:59.999Z"
            }
        },
        "last_updated": "2024-07-04T11:01:59.999Z"
    }
}