{
    "data": {
        "quote": {
            "USD": {
                "total_market_cap": 2173859017511.8542,
                "total_volume_24h": 66610953984.03,
                "total_volume_24h_reported": 382701980527.12,
                "altcoin_volume_24h": 41076661392.892044,
                "altcoin_volume_24h_reported": 252559196690.63226,
                "altcoin_market_cap": 916209133707.8109,
                "defi_volume_24h": 9802653173.554667,
                "defi_market_cap": 68077500717.56364,
                "defi_volume_24h_reported": 62378994206.03143,
                "defi_24h_percentage_change": -7.3153188859,
                "stablecoin_volume_24h": 68370923657.96118,
                "stablecoin_volume_24h_reported": 381187982999.68677,
                "stablecoin_market_cap": 282929582027.07996,
                "stablecoin_24h_percentage_change": -28.2808646942,
                "derivatives_volume_24h": 554804446806.492,
                "derivatives_volume_24h_reported": 584861445543.0687,
                "derivatives_24h_percentage_change": -34.3204137363,
                "total_market_cap_yesterday": 2126521320128.613,
                "total_volume_24h_yesterday": 93284885168.9,
                "total_market_cap_yesterday_percentage_change": 2.22606267,
                "total_volume_24h_yesterday_percentage_change": -28.5940548,
                "last_updated": "2026-07-03T20:56:59.999Z"
            }
        },
        "btc_dominance": 57.853332422795,
        "eth_dominance": 9.79421238228,
        "active_cryptocurrencies": 8203,
        "total_cryptocurrencies": 38270,
        "active_market_pairs": 112834,
        "active_exchanges": 952,
        "total_exchanges": 12336,
        "last_updated": "2026-07-03T20:56:59.999Z",
        "eth_dominance_yesterday": 9.65415708,
        "btc_dominance_yesterday": 57.93064975,
        "eth_dominance_24h_percentage_change": 0.14005530228,
        "btc_dominance_24h_percentage_change": -0.077317327205,
        "defi_volume_24h": 9802653173.554667,
        "defi_volume_24h_reported": 62378994206.03143,
        "defi_market_cap": 68077500717.56364,
        "defi_24h_percentage_change": -7.315318885932,
        "stablecoin_volume_24h": 68370923657.96118,
        "stablecoin_volume_24h_reported": 381187982999.68677,
        "stablecoin_market_cap": 282929582027.07996,
        "stablecoin_24h_percentage_change": -28.280864694238,
        "derivatives_volume_24h": 554804446806.492,
        "derivatives_volume_24h_reported": 584861445543.0687,
        "derivatives_24h_percentage_change": -34.320413736288,
        "total_crypto_dex_currencies": 53276433,
        "today_incremental_crypto_number": 9,
        "past_24h_incremental_crypto_number": 64047,
        "past_7d_incremental_crypto_number": 332046,
        "past_30d_incremental_crypto_number": 1504612,
        "today_change_percent": 4.3171077e-05,
        "tracked_yearly_number": {
            "maxIncrementalNumber": 7681147,
            "minIncrementalNumber": 24,
            "maxIncrementalDate": "2026-03-19T00:00:00.000Z",
            "minIncrementalDate": "2026-07-03T00:00:00.000Z"
        }
    },
    "status": {
        "timestamp": "2026-07-03T20:58:30.724Z",
        "error_code": 0,
        "error_message": null,
        "elapsed": 29,
        "credit_count": 1,
        "notice": null
    }
}