{
    "status": {
        "timestamp": "2025-05-12T22:03:12.544Z",
        "error_code": 0,
        "error_message": null,
        "elapsed": 79,
        "credit_count": 1,
        "notice": null
    },
    "data": {
        "active_cryptocurrencies": 9811,
        "total_cryptocurrencies": 34486,
        "active_market_pairs": 102058,
        "active_exchanges": 815,
        "total_exchanges": 10419,
        "eth_dominance": 9.053239985123,
        "btc_dominance": 61.600844854838,
        "eth_dominance_yesterday": 9.13363668,
        "btc_dominance_yesterday": 62.15456781,
        "eth_dominance_24h_percentage_change": -0.080396694877,
        "btc_dominance_24h_percentage_change": -0.553722955162,
        "defi_volume_24h": 27258126192.31869,
        "defi_volume_24h_reported": 61142650610.93216,
        "defi_market_cap": 74790402041.32593,
        "defi_24h_percentage_change": 2.291523604026,
        "stablecoin_volume_24h": 168225298239.34158,
        "stablecoin_volume_24h_reported": 996631193981.1069,
        "stablecoin_market_cap": 226806434408.31314,
        "stablecoin_24h_percentage_change": 32.010139295406,
        "derivatives_volume_24h": 1886583406067.7542,
        "derivatives_volume_24h_reported": 1886583406067.7542,
        "derivatives_24h_percentage_change": 22.322152483861,
        "total_crypto_dex_currencies": 15318836,
        "today_incremental_crypto_number": 0,
        "past_24h_incremental_crypto_number": 50854,
        "past_7d_incremental_crypto_number": 334932,
        "past_30d_incremental_crypto_number": 2025450,
        "today_change_percent": 0.014859733517,
        "tracked_yearly_number": {
            "maxIncrementalNumber": 184087,
            "minIncrementalNumber": 2276,
            "maxIncrementalDate": "2025-04-17T00:00:00.000Z",
            "minIncrementalDate": "2025-05-12T00:00:00.000Z"
        },
        "quote": {
            "USD": {
                "total_market_cap": 3302908763710.1104,
                "total_volume_24h": 180958524220.75,
                "total_volume_24h_reported": 1024734240111.95,
                "altcoin_volume_24h": 116785692996.61363,
                "altcoin_volume_24h_reported": 709560863053.9701,
                "altcoin_market_cap": 1268289060480.188,
                "defi_volume_24h": 27258126192.31869,
                "defi_volume_24h_reported": 61142650610.93216,
                "defi_24h_percentage_change": 2.291523604026,
                "defi_market_cap": 74790402041.32593,
                "stablecoin_volume_24h": 168225298239.34158,
                "stablecoin_volume_24h_reported": 996631193981.1069,
                "stablecoin_24h_percentage_change": 32.010139295406,
                "stablecoin_market_cap": 226806434408.31314,
                "derivatives_volume_24h": 1886583406067.7542,
                "derivatives_volume_24h_reported": 1886583406067.7542,
                "derivatives_24h_percentage_change": 22.322152483861,
                "total_market_cap_yesterday": 3339892899801.587,
                "total_volume_24h_yesterday": 136683092395.54,
                "total_market_cap_yesterday_percentage_change": -1.1073449718604422,
                "total_volume_24h_yesterday_percentage_change": 32.39276420311273,
                "last_updated": "2025-05-12T22:01:59.999Z"
            }
        },
        "last_updated": "2025-05-12T22:01:59.999Z"
    }
}