{
    "status": {
        "timestamp": "2025-07-26T10:03:33.933Z",
        "error_code": 0,
        "error_message": null,
        "elapsed": 26,
        "credit_count": 1,
        "notice": null
    },
    "data": {
        "active_cryptocurrencies": 9461,
        "total_cryptocurrencies": 35426,
        "active_market_pairs": 106170,
        "active_exchanges": 835,
        "total_exchanges": 10767,
        "eth_dominance": 11.713612453525,
        "btc_dominance": 60.384140164861,
        "eth_dominance_yesterday": 11.79301683,
        "btc_dominance_yesterday": 60.46339391,
        "eth_dominance_24h_percentage_change": -0.079404376475,
        "btc_dominance_24h_percentage_change": -0.079253745139,
        "defi_volume_24h": 41496889702.44139,
        "defi_volume_24h_reported": 93827448064.74458,
        "defi_market_cap": 113661109102.65022,
        "defi_24h_percentage_change": -14.647862695333,
        "stablecoin_volume_24h": 152109151565.6426,
        "stablecoin_volume_24h_reported": 784870065470.7883,
        "stablecoin_market_cap": 246738455904.13724,
        "stablecoin_24h_percentage_change": -29.833638327899,
        "derivatives_volume_24h": 1535275724315.0784,
        "derivatives_volume_24h_reported": 1535275724315.0784,
        "derivatives_24h_percentage_change": -29.141488938516,
        "total_crypto_dex_currencies": 18847525,
        "today_incremental_crypto_number": 0,
        "past_24h_incremental_crypto_number": 26398,
        "past_7d_incremental_crypto_number": 180331,
        "past_30d_incremental_crypto_number": 1153760,
        "today_change_percent": 0.021965266752,
        "tracked_yearly_number": {
            "maxIncrementalNumber": 184087,
            "minIncrementalNumber": 4140,
            "maxIncrementalDate": "2025-04-17T00:00:00.000Z",
            "minIncrementalDate": "2025-07-26T00:00:00.000Z"
        },
        "quote": {
            "USD": {
                "total_market_cap": 3876574291343.889,
                "total_volume_24h": 160080868107.06,
                "total_volume_24h_reported": 803119475947.59,
                "altcoin_volume_24h": 92787715322.69556,
                "altcoin_volume_24h_reported": 546953319432.4629,
                "altcoin_market_cap": 1535738237663.8103,
                "defi_volume_24h": 41496889702.44139,
                "defi_volume_24h_reported": 93827448064.74458,
                "defi_24h_percentage_change": -14.647862695333,
                "defi_market_cap": 113661109102.65022,
                "stablecoin_volume_24h": 152109151565.6426,
                "stablecoin_volume_24h_reported": 784870065470.7883,
                "stablecoin_24h_percentage_change": -29.833638327899,
                "stablecoin_market_cap": 246738455904.13724,
                "derivatives_volume_24h": 1535275724315.0784,
                "derivatives_volume_24h_reported": 1535275724315.0784,
                "derivatives_24h_percentage_change": -29.141488938516,
                "total_market_cap_yesterday": 3823621122663.039,
                "total_volume_24h_yesterday": 226242930500.48,
                "total_market_cap_yesterday_percentage_change": 1.3848958090274692,
                "total_volume_24h_yesterday_percentage_change": -29.24381426949367,
                "last_updated": "2025-07-26T10:01:59.999Z"
            }
        },
        "last_updated": "2025-07-26T10:01:59.999Z"
    }
}