{
    "status": {
        "timestamp": "2025-03-23T00:14:51.486Z",
        "error_code": 0,
        "error_message": null,
        "elapsed": 12,
        "credit_count": 1,
        "notice": null
    },
    "data": {
        "active_cryptocurrencies": 10519,
        "total_cryptocurrencies": 34144,
        "active_market_pairs": 102788,
        "active_exchanges": 813,
        "total_exchanges": 10240,
        "eth_dominance": 8.690494241391,
        "btc_dominance": 60.495259162858,
        "eth_dominance_yesterday": 8.63182881,
        "btc_dominance_yesterday": 60.58858959,
        "eth_dominance_24h_percentage_change": 0.058665431391,
        "btc_dominance_24h_percentage_change": -0.093330427142,
        "defi_volume_24h": 5979387965.349166,
        "defi_volume_24h_reported": 38184650382.92088,
        "defi_market_cap": 69569554456.45522,
        "defi_24h_percentage_change": 5.740606692238,
        "stablecoin_volume_24h": 39009931730.23371,
        "stablecoin_volume_24h_reported": 248388328505.58057,
        "stablecoin_market_cap": 218045777500.2414,
        "stablecoin_24h_percentage_change": -35.695288437298,
        "derivatives_volume_24h": 532790935151.0898,
        "derivatives_volume_24h_reported": 544025392039.83405,
        "derivatives_24h_percentage_change": -28.831690021615,
        "total_crypto_dex_currencies": 13099700,
        "quote": {
            "USD": {
                "total_market_cap": 2750721580472.9907,
                "total_volume_24h": 41998297581.63,
                "total_volume_24h_reported": 254135053385.47,
                "altcoin_volume_24h": 32178787425.25619,
                "altcoin_volume_24h_reported": 199130213612.25473,
                "altcoin_market_cap": 1086665431517.1793,
                "defi_volume_24h": 5979387965.349166,
                "defi_volume_24h_reported": 38184650382.92088,
                "defi_24h_percentage_change": 5.740606692238,
                "defi_market_cap": 69569554456.45522,
                "stablecoin_volume_24h": 39009931730.23371,
                "stablecoin_volume_24h_reported": 248388328505.58057,
                "stablecoin_24h_percentage_change": -35.695288437298,
                "stablecoin_market_cap": 218045777500.2414,
                "derivatives_volume_24h": 532790935151.0898,
                "derivatives_volume_24h_reported": 544025392039.83405,
                "derivatives_24h_percentage_change": -28.831690021615,
                "total_market_cap_yesterday": 2753421888912.7085,
                "total_volume_24h_yesterday": 62869356656.42,
                "total_market_cap_yesterday_percentage_change": -0.09807100214432296,
                "total_volume_24h_yesterday_percentage_change": -33.19750699669156,
                "last_updated": "2025-03-23T00:12:59.999Z"
            }
        },
        "last_updated": "2025-03-23T00:12:59.999Z"
    }
}