{
    "status": {
        "timestamp": "2025-07-04T04:09:41.438Z",
        "error_code": 0,
        "error_message": null,
        "elapsed": 15,
        "credit_count": 1,
        "notice": null
    },
    "data": {
        "active_cryptocurrencies": 9502,
        "total_cryptocurrencies": 35096,
        "active_market_pairs": 104161,
        "active_exchanges": 829,
        "total_exchanges": 10600,
        "eth_dominance": 9.237683306192,
        "btc_dominance": 64.459516510521,
        "eth_dominance_yesterday": 9.21904361,
        "btc_dominance_yesterday": 64.39716224,
        "eth_dominance_24h_percentage_change": 0.018639696192,
        "btc_dominance_24h_percentage_change": 0.062354270521,
        "defi_volume_24h": 34301849697.75422,
        "defi_volume_24h_reported": 66616305584.08,
        "defi_market_cap": 87210922370.37819,
        "defi_24h_percentage_change": -4.580492190702,
        "stablecoin_volume_24h": 108591033764.66322,
        "stablecoin_volume_24h_reported": 601910117587.9006,
        "stablecoin_market_cap": 237934768452.6544,
        "stablecoin_24h_percentage_change": -11.884940852529,
        "derivatives_volume_24h": 1035502636988.498,
        "derivatives_volume_24h_reported": 1035502636988.498,
        "derivatives_24h_percentage_change": -16.152604472815,
        "total_crypto_dex_currencies": 18131619,
        "today_incremental_crypto_number": 0,
        "past_24h_incremental_crypto_number": 51002,
        "past_7d_incremental_crypto_number": 353857,
        "past_30d_incremental_crypto_number": 1458061,
        "today_change_percent": 0.011947409555,
        "tracked_yearly_number": {
            "maxIncrementalNumber": 184087,
            "minIncrementalNumber": 2167,
            "maxIncrementalDate": "2025-04-17T00:00:00.000Z",
            "minIncrementalDate": "2025-07-04T00:00:00.000Z"
        },
        "quote": {
            "USD": {
                "total_market_cap": 3372515339113.869,
                "total_volume_24h": 113143583598.34,
                "total_volume_24h_reported": 614570556422.23,
                "altcoin_volume_24h": 63793035073.15012,
                "altcoin_volume_24h_reported": 402035850311.06665,
                "altcoin_market_cap": 1198608257277.9163,
                "defi_volume_24h": 34301849697.75422,
                "defi_volume_24h_reported": 66616305584.08,
                "defi_24h_percentage_change": -4.580492190702,
                "defi_market_cap": 87210922370.37819,
                "stablecoin_volume_24h": 108591033764.66322,
                "stablecoin_volume_24h_reported": 601910117587.9006,
                "stablecoin_24h_percentage_change": -11.884940852529,
                "stablecoin_market_cap": 237934768452.6544,
                "derivatives_volume_24h": 1035502636988.498,
                "derivatives_volume_24h_reported": 1035502636988.498,
                "derivatives_24h_percentage_change": -16.152604472815,
                "total_market_cap_yesterday": 3359628223543.359,
                "total_volume_24h_yesterday": 127747617168.99,
                "total_market_cap_yesterday_percentage_change": 0.38358754936635364,
                "total_volume_24h_yesterday_percentage_change": -11.43194205441121,
                "last_updated": "2025-07-04T04:07:59.999Z"
            }
        },
        "last_updated": "2025-07-04T04:07:59.999Z"
    }
}