{
    "status": {
        "timestamp": "2024-09-14T00:11:31.822Z",
        "error_code": 0,
        "error_message": null,
        "elapsed": 21,
        "credit_count": 1,
        "notice": null
    },
    "data": {
        "active_cryptocurrencies": 9874,
        "total_cryptocurrencies": 31328,
        "active_market_pairs": 83793,
        "active_exchanges": 794,
        "total_exchanges": 9243,
        "eth_dominance": 13.879278390948,
        "btc_dominance": 56.605804707934,
        "eth_dominance_yesterday": 13.88315616,
        "btc_dominance_yesterday": 56.17206319,
        "eth_dominance_24h_percentage_change": -0.003877769052,
        "btc_dominance_24h_percentage_change": 0.433741517934,
        "defi_volume_24h": 3988880919.9354672,
        "defi_volume_24h_reported": 24493667670.37752,
        "defi_market_cap": 58762534144.16457,
        "defi_24h_percentage_change": 39.276221646479,
        "stablecoin_volume_24h": 61095603567.762215,
        "stablecoin_volume_24h_reported": 341812209326.6983,
        "stablecoin_market_cap": 164799401942.23166,
        "stablecoin_24h_percentage_change": 2.606304292116,
        "derivatives_volume_24h": 602132320377.2095,
        "derivatives_volume_24h_reported": 616063201066.142,
        "derivatives_24h_percentage_change": 4.35091420008,
        "quote": {
            "USD": {
                "total_market_cap": 2115754646165.4758,
                "total_volume_24h": 66352435778.86,
                "total_volume_24h_reported": 353962329802.78,
                "altcoin_volume_24h": 33762832779.57431,
                "altcoin_volume_24h_reported": 186822990811.63223,
                "altcoin_market_cap": 918114703057.9971,
                "defi_volume_24h": 3988880919.9354672,
                "defi_volume_24h_reported": 24493667670.37752,
                "defi_24h_percentage_change": 39.276221646479,
                "defi_market_cap": 58762534144.16457,
                "stablecoin_volume_24h": 61095603567.762215,
                "stablecoin_volume_24h_reported": 341812209326.6983,
                "stablecoin_24h_percentage_change": 2.606304292116,
                "stablecoin_market_cap": 164799401942.23166,
                "derivatives_volume_24h": 602132320377.2095,
                "derivatives_volume_24h_reported": 616063201066.142,
                "derivatives_24h_percentage_change": 4.35091420008,
                "total_market_cap_yesterday": 2047023892305.0203,
                "total_volume_24h_yesterday": 64781986236.85,
                "total_market_cap_yesterday_percentage_change": 3.3575941208513314,
                "total_volume_24h_yesterday_percentage_change": 2.4242071496052517,
                "last_updated": "2024-09-14T00:08:59.999Z"
            }
        },
        "last_updated": "2024-09-14T00:08:59.999Z"
    }
}