{
    "status": {
        "timestamp": "2026-03-23T19:19:18.786Z",
        "error_code": 0,
        "error_message": null,
        "elapsed": 14,
        "credit_count": 1,
        "notice": null
    },
    "data": {
        "active_cryptocurrencies": 8549,
        "total_cryptocurrencies": 37321,
        "active_market_pairs": 116593,
        "active_exchanges": 931,
        "total_exchanges": 11957,
        "eth_dominance": 10.752644467643,
        "btc_dominance": 58.401011228447,
        "eth_dominance_yesterday": 10.58757666,
        "btc_dominance_yesterday": 58.16499492,
        "eth_dominance_24h_percentage_change": 0.165067807643,
        "btc_dominance_24h_percentage_change": 0.236016308447,
        "defi_volume_24h": 13019041258.185547,
        "defi_volume_24h_reported": 40800364659.06965,
        "defi_market_cap": 59656611197.34674,
        "defi_24h_percentage_change": 60.05322037903,
        "stablecoin_volume_24h": 126545756083.17813,
        "stablecoin_volume_24h_reported": 803633721599.6244,
        "stablecoin_market_cap": 289619591751.8625,
        "stablecoin_24h_percentage_change": 87.913865908918,
        "derivatives_volume_24h": 1208432643426.151,
        "derivatives_volume_24h_reported": 1251048842528.0325,
        "derivatives_24h_percentage_change": 109.671609617702,
        "total_crypto_dex_currencies": 46861818,
        "today_incremental_crypto_number": 1,
        "past_24h_incremental_crypto_number": 90900,
        "past_7d_incremental_crypto_number": 8687967,
        "past_30d_incremental_crypto_number": 11621515,
        "today_change_percent": 0.000307287358,
        "tracked_yearly_number": {
            "maxIncrementalNumber": 7681151,
            "minIncrementalNumber": 145,
            "maxIncrementalDate": "2026-03-19T00:00:00.000Z",
            "minIncrementalDate": "2026-03-23T00:00:00.000Z"
        },
        "quote": {
            "USD": {
                "total_market_cap": 2427504780486.901,
                "total_volume_24h": 128690143531.43,
                "total_volume_24h_reported": 816067163947.8,
                "altcoin_volume_24h": 75408215633.01157,
                "altcoin_volume_24h_reported": 528103200243.8337,
                "altcoin_market_cap": 1009817441063.6598,
                "defi_volume_24h": 13019041258.185547,
                "defi_volume_24h_reported": 40800364659.06965,
                "defi_24h_percentage_change": 60.05322037903,
                "defi_market_cap": 59656611197.34674,
                "stablecoin_volume_24h": 126545756083.17813,
                "stablecoin_volume_24h_reported": 803633721599.6244,
                "stablecoin_24h_percentage_change": 87.913865908918,
                "stablecoin_market_cap": 289619591751.8625,
                "derivatives_volume_24h": 1208432643426.151,
                "derivatives_volume_24h_reported": 1251048842528.0325,
                "derivatives_24h_percentage_change": 109.671609617702,
                "total_market_cap_yesterday": 2350606555614.019,
                "total_volume_24h_yesterday": 69841167854.39,
                "total_market_cap_yesterday_percentage_change": 3.271420505878524,
                "total_volume_24h_yesterday_percentage_change": 84.26115639952167,
                "last_updated": "2026-03-23T19:16:59.999Z"
            }
        },
        "last_updated": "2026-03-23T19:16:59.999Z"
    }
}