{
    "status": {
        "timestamp": "2024-11-29T05:03:20.371Z",
        "error_code": 0,
        "error_message": null,
        "elapsed": 18,
        "credit_count": 1,
        "notice": null
    },
    "data": {
        "active_cryptocurrencies": 10252,
        "total_cryptocurrencies": 32493,
        "active_market_pairs": 91277,
        "active_exchanges": 762,
        "total_exchanges": 9643,
        "eth_dominance": 12.915219972951,
        "btc_dominance": 57.085063561542,
        "eth_dominance_yesterday": 13.07088515,
        "btc_dominance_yesterday": 57.03804959,
        "eth_dominance_24h_percentage_change": -0.155665177049,
        "btc_dominance_24h_percentage_change": 0.047013971542,
        "defi_volume_24h": 9758642213.672613,
        "defi_volume_24h_reported": 46065766369.98324,
        "defi_market_cap": 95218666987.25888,
        "defi_24h_percentage_change": -37.83246317627,
        "stablecoin_volume_24h": 135787913433.37086,
        "stablecoin_volume_24h_reported": 684494772717.4618,
        "stablecoin_market_cap": 182328743875.37497,
        "stablecoin_24h_percentage_change": -26.764214681596,
        "derivatives_volume_24h": 1285267753602.744,
        "derivatives_volume_24h_reported": 1344718580085.1394,
        "derivatives_24h_percentage_change": -21.333087947786,
        "quote": {
            "USD": {
                "total_market_cap": 3337865543537.7764,
                "total_volume_24h": 147775995843.52,
                "total_volume_24h_reported": 706250750905.31,
                "altcoin_volume_24h": 99073274933.93297,
                "altcoin_volume_24h_reported": 490697119578.9716,
                "altcoin_market_cap": 1432442876410.4111,
                "defi_volume_24h": 9758642213.672613,
                "defi_volume_24h_reported": 46065766369.98324,
                "defi_24h_percentage_change": -37.83246317627,
                "defi_market_cap": 95218666987.25888,
                "stablecoin_volume_24h": 135787913433.37086,
                "stablecoin_volume_24h_reported": 684494772717.4618,
                "stablecoin_24h_percentage_change": -26.764214681596,
                "stablecoin_market_cap": 182328743875.37497,
                "derivatives_volume_24h": 1285267753602.744,
                "derivatives_volume_24h_reported": 1344718580085.1394,
                "derivatives_24h_percentage_change": -21.333087947786,
                "total_market_cap_yesterday": 3324620623997.0376,
                "total_volume_24h_yesterday": 202128382537.14,
                "total_market_cap_yesterday_percentage_change": 0.39838890022932105,
                "total_volume_24h_yesterday_percentage_change": -26.890031974422527,
                "last_updated": "2024-11-29T05:00:59.999Z"
            }
        },
        "last_updated": "2024-11-29T05:00:59.999Z"
    }
}