{
    "status": {
        "timestamp": "2025-01-04T23:03:02.246Z",
        "error_code": 0,
        "error_message": null,
        "elapsed": 57,
        "credit_count": 1,
        "notice": null
    },
    "data": {
        "active_cryptocurrencies": 10528,
        "total_cryptocurrencies": 33146,
        "active_market_pairs": 96030,
        "active_exchanges": 773,
        "total_exchanges": 9845,
        "eth_dominance": 12.558346735175,
        "btc_dominance": 55.506986031345,
        "eth_dominance_yesterday": 12.44165264,
        "btc_dominance_yesterday": 55.60943597,
        "eth_dominance_24h_percentage_change": 0.116694095175,
        "btc_dominance_24h_percentage_change": -0.102449938655,
        "defi_volume_24h": 8705454695.177498,
        "defi_volume_24h_reported": 42021569662.45776,
        "defi_market_cap": 118991326249.88817,
        "defi_24h_percentage_change": -13.217980110002,
        "stablecoin_volume_24h": 84680779800.4495,
        "stablecoin_volume_24h_reported": 438527015145.5471,
        "stablecoin_market_cap": 198143136118.03232,
        "stablecoin_24h_percentage_change": -24.440075912203,
        "derivatives_volume_24h": 944540809073.0598,
        "derivatives_volume_24h_reported": 960161522119.3556,
        "derivatives_24h_percentage_change": -17.488227028248,
        "quote": {
            "USD": {
                "total_market_cap": 3510232915266.979,
                "total_volume_24h": 93254346351.67,
                "total_volume_24h_reported": 451955988607.19,
                "altcoin_volume_24h": 70607002177.12473,
                "altcoin_volume_24h_reported": 358115886319.9432,
                "altcoin_market_cap": 1561808421322.0583,
                "defi_volume_24h": 8705454695.177498,
                "defi_volume_24h_reported": 42021569662.45776,
                "defi_24h_percentage_change": -13.217980110002,
                "defi_market_cap": 118991326249.88817,
                "stablecoin_volume_24h": 84680779800.4495,
                "stablecoin_volume_24h_reported": 438527015145.5471,
                "stablecoin_24h_percentage_change": -24.440075912203,
                "stablecoin_market_cap": 198143136118.03232,
                "derivatives_volume_24h": 944540809073.0598,
                "derivatives_volume_24h_reported": 960161522119.3556,
                "derivatives_24h_percentage_change": -17.488227028248,
                "total_market_cap_yesterday": 3501075788580.1274,
                "total_volume_24h_yesterday": 121425709997.47,
                "total_market_cap_yesterday_percentage_change": 0.2615517983563791,
                "total_volume_24h_yesterday_percentage_change": -23.200493245118338,
                "last_updated": "2025-01-04T23:00:59.999Z"
            }
        },
        "last_updated": "2025-01-04T23:00:59.999Z"
    }
}