{
    "status": {
        "timestamp": "2025-08-03T09:03:47.719Z",
        "error_code": 0,
        "error_message": null,
        "elapsed": 23,
        "credit_count": 1,
        "notice": null
    },
    "data": {
        "active_cryptocurrencies": 9478,
        "total_cryptocurrencies": 35498,
        "active_market_pairs": 106624,
        "active_exchanges": 836,
        "total_exchanges": 10801,
        "eth_dominance": 11.363422836315,
        "btc_dominance": 61.498580786504,
        "eth_dominance_yesterday": 11.42117062,
        "btc_dominance_yesterday": 61.33765415,
        "eth_dominance_24h_percentage_change": -0.057747783685,
        "btc_dominance_24h_percentage_change": 0.160926636504,
        "defi_volume_24h": 33442141651.976444,
        "defi_volume_24h_reported": 66011562570.863045,
        "defi_market_cap": 99653885603.78616,
        "defi_24h_percentage_change": -15.359902746528,
        "stablecoin_volume_24h": 123766595329.32048,
        "stablecoin_volume_24h_reported": 647603151230.2848,
        "stablecoin_market_cap": 249362198189.44763,
        "stablecoin_24h_percentage_change": -26.00566629595,
        "derivatives_volume_24h": 1174983175561.8977,
        "derivatives_volume_24h_reported": 1174983175561.8977,
        "derivatives_24h_percentage_change": -33.629512988124,
        "total_crypto_dex_currencies": 19013419,
        "today_incremental_crypto_number": 0,
        "past_24h_incremental_crypto_number": 27293,
        "past_7d_incremental_crypto_number": 138193,
        "past_30d_incremental_crypto_number": 864193,
        "today_change_percent": 0.008673574317,
        "tracked_yearly_number": {
            "maxIncrementalNumber": 184087,
            "minIncrementalNumber": 1649,
            "maxIncrementalDate": "2025-04-17T00:00:00.000Z",
            "minIncrementalDate": "2025-08-03T00:00:00.000Z"
        },
        "quote": {
            "USD": {
                "total_market_cap": 3679192502600.8857,
                "total_volume_24h": 129757081741.84,
                "total_volume_24h_reported": 663676955339.88,
                "altcoin_volume_24h": 73535890208.74817,
                "altcoin_volume_24h_reported": 479359748911.886,
                "altcoin_market_cap": 1416541329097.8855,
                "defi_volume_24h": 33442141651.976444,
                "defi_volume_24h_reported": 66011562570.863045,
                "defi_24h_percentage_change": -15.359902746528,
                "defi_market_cap": 99653885603.78616,
                "stablecoin_volume_24h": 123766595329.32048,
                "stablecoin_volume_24h_reported": 647603151230.2848,
                "stablecoin_24h_percentage_change": -26.00566629595,
                "stablecoin_market_cap": 249362198189.44763,
                "derivatives_volume_24h": 1174983175561.8977,
                "derivatives_volume_24h_reported": 1174983175561.8977,
                "derivatives_24h_percentage_change": -33.629512988124,
                "total_market_cap_yesterday": 3687978138797.105,
                "total_volume_24h_yesterday": 173820142330.65,
                "total_market_cap_yesterday_percentage_change": -0.23822365170214255,
                "total_volume_24h_yesterday_percentage_change": -25.349801235918264,
                "last_updated": "2025-08-03T09:01:59.999Z"
            }
        },
        "last_updated": "2025-08-03T09:01:59.999Z"
    }
}