{
    "status": {
        "timestamp": "2025-10-19T03:24:22.223Z",
        "error_code": 0,
        "error_message": null,
        "elapsed": 23,
        "credit_count": 1,
        "notice": null
    },
    "data": {
        "active_cryptocurrencies": 9474,
        "total_cryptocurrencies": 36325,
        "active_market_pairs": 114799,
        "active_exchanges": 872,
        "total_exchanges": 11302,
        "eth_dominance": 12.903586019576,
        "btc_dominance": 58.816735312321,
        "eth_dominance_yesterday": 12.88322524,
        "btc_dominance_yesterday": 58.84271961,
        "eth_dominance_24h_percentage_change": 0.020360779576,
        "btc_dominance_24h_percentage_change": -0.025984297679,
        "defi_volume_24h": 14802798845.083008,
        "defi_volume_24h_reported": 46542123997.4421,
        "defi_market_cap": 94175640387.79485,
        "defi_24h_percentage_change": -36.442060455587,
        "stablecoin_volume_24h": 101449560852.87933,
        "stablecoin_volume_24h_reported": 450715423823.3555,
        "stablecoin_market_cap": 284371491713.9489,
        "stablecoin_24h_percentage_change": -57.150774388635,
        "derivatives_volume_24h": 898465284297.7018,
        "derivatives_volume_24h_reported": 898465284297.7018,
        "derivatives_24h_percentage_change": -58.194726420231,
        "total_crypto_dex_currencies": 25516842,
        "today_incremental_crypto_number": 0,
        "past_24h_incremental_crypto_number": 50569,
        "past_7d_incremental_crypto_number": 283709,
        "past_30d_incremental_crypto_number": 1350808,
        "today_change_percent": 3.91898e-06,
        "tracked_yearly_number": {
            "maxIncrementalNumber": 184087,
            "minIncrementalNumber": 1,
            "maxIncrementalDate": "2025-04-17T00:00:00.000Z",
            "minIncrementalDate": "2025-10-19T00:00:00.000Z"
        },
        "quote": {
            "USD": {
                "total_market_cap": 3631490626656.0483,
                "total_volume_24h": 103127375311.73,
                "total_volume_24h_reported": 456708954061.95,
                "altcoin_volume_24h": 69936397427.74689,
                "altcoin_volume_24h_reported": 330332655172.59235,
                "altcoin_market_cap": 1495566396884.029,
                "defi_volume_24h": 14802798845.083008,
                "defi_volume_24h_reported": 46542123997.4421,
                "defi_24h_percentage_change": -36.442060455587,
                "defi_market_cap": 94175640387.79485,
                "stablecoin_volume_24h": 101449560852.87933,
                "stablecoin_volume_24h_reported": 450715423823.3555,
                "stablecoin_24h_percentage_change": -57.150774388635,
                "stablecoin_market_cap": 284371491713.9489,
                "derivatives_volume_24h": 898465284297.7018,
                "derivatives_volume_24h_reported": 898465284297.7018,
                "derivatives_24h_percentage_change": -58.194726420231,
                "total_market_cap_yesterday": 3624179547713.5854,
                "total_volume_24h_yesterday": 241661805783.72,
                "total_market_cap_yesterday_percentage_change": 0.20173059436514507,
                "total_volume_24h_yesterday_percentage_change": -57.32574496938673,
                "last_updated": "2025-10-19T03:21:59.999Z"
            }
        },
        "last_updated": "2025-10-19T03:21:59.999Z"
    }
}