{
    "status": {
        "timestamp": "2024-07-26T02:16:35.108Z",
        "error_code": 0,
        "error_message": null,
        "elapsed": 20,
        "credit_count": 1,
        "notice": null
    },
    "data": {
        "active_cryptocurrencies": 10050,
        "total_cryptocurrencies": 30791,
        "active_market_pairs": 82294,
        "active_exchanges": 794,
        "total_exchanges": 9013,
        "eth_dominance": 16.224113394354,
        "btc_dominance": 55.44328094528,
        "eth_dominance_yesterday": 16.61788406,
        "btc_dominance_yesterday": 54.74547947,
        "eth_dominance_24h_percentage_change": -0.393770665646,
        "btc_dominance_24h_percentage_change": 0.69780147528,
        "defi_volume_24h": 4756497719.713582,
        "defi_volume_24h_reported": 25671091419.660633,
        "defi_market_cap": 71082150931.60895,
        "defi_24h_percentage_change": 8.578932320925,
        "stablecoin_volume_24h": 77048989265.34572,
        "stablecoin_volume_24h_reported": 422427578538.99927,
        "stablecoin_market_cap": 157709272863.25797,
        "stablecoin_24h_percentage_change": 11.852179109224,
        "derivatives_volume_24h": 700176101740.7925,
        "derivatives_volume_24h_reported": 702963867764.4718,
        "derivatives_24h_percentage_change": 7.813126413212,
        "quote": {
            "USD": {
                "total_market_cap": 2366658122468.26,
                "total_volume_24h": 84206751771.91,
                "total_volume_24h_reported": 441083161427.39,
                "altcoin_volume_24h": 48442493030.04411,
                "altcoin_volume_24h_reported": 261892706104.83386,
                "altcoin_market_cap": 1054505210613.8883,
                "defi_volume_24h": 4756497719.713582,
                "defi_volume_24h_reported": 25671091419.660633,
                "defi_24h_percentage_change": 8.578932320925,
                "defi_market_cap": 71082150931.60895,
                "stablecoin_volume_24h": 77048989265.34572,
                "stablecoin_volume_24h_reported": 422427578538.99927,
                "stablecoin_24h_percentage_change": 11.852179109224,
                "stablecoin_market_cap": 157709272863.25797,
                "derivatives_volume_24h": 700176101740.7925,
                "derivatives_volume_24h_reported": 702963867764.4718,
                "derivatives_24h_percentage_change": 7.813126413212,
                "total_market_cap_yesterday": 2317655348113.5737,
                "total_volume_24h_yesterday": 75162980619.22,
                "total_market_cap_yesterday_percentage_change": 2.114325341538432,
                "total_volume_24h_yesterday_percentage_change": 12.032214633033618,
                "last_updated": "2024-07-26T02:14:59.999Z"
            }
        },
        "last_updated": "2024-07-26T02:14:59.999Z"
    }
}