{
    "status": {
        "timestamp": "2026-02-06T01:33:48.003Z",
        "error_code": 0,
        "error_message": null,
        "elapsed": 23,
        "credit_count": 1,
        "notice": null
    },
    "data": {
        "active_cryptocurrencies": 8945,
        "total_cryptocurrencies": 37080,
        "active_market_pairs": 119367,
        "active_exchanges": 922,
        "total_exchanges": 11795,
        "eth_dominance": 10.364235485753,
        "btc_dominance": 58.079069580012,
        "eth_dominance_yesterday": 10.52410466,
        "btc_dominance_yesterday": 58.73924061,
        "eth_dominance_24h_percentage_change": -0.159869174247,
        "btc_dominance_24h_percentage_change": -0.660171029988,
        "defi_volume_24h": 29323094889.041363,
        "defi_volume_24h_reported": 85311752794.61522,
        "defi_market_cap": 55329213758.10103,
        "defi_24h_percentage_change": 79.523575486318,
        "stablecoin_volume_24h": 300838412867.2987,
        "stablecoin_volume_24h_reported": 1666369625368.8372,
        "stablecoin_market_cap": 283193672220.0623,
        "stablecoin_24h_percentage_change": 84.157196161854,
        "derivatives_volume_24h": 2654454367650.1216,
        "derivatives_volume_24h_reported": 2723597883958.2993,
        "derivatives_24h_percentage_change": 82.290001191703,
        "total_crypto_dex_currencies": 32346519,
        "today_incremental_crypto_number": 3,
        "past_24h_incremental_crypto_number": 157996,
        "past_7d_incremental_crypto_number": 947404,
        "past_30d_incremental_crypto_number": 2796851,
        "today_change_percent": 0.000105111885,
        "tracked_yearly_number": {
            "maxIncrementalNumber": 1305553,
            "minIncrementalNumber": 35,
            "maxIncrementalDate": "2025-07-08T00:00:00.000Z",
            "minIncrementalDate": "2026-02-05T00:00:00.000Z"
        },
        "quote": {
            "USD": {
                "total_market_cap": 2205946461722.195,
                "total_volume_24h": 306656027061.05,
                "total_volume_24h_reported": 1699125902157.48,
                "altcoin_volume_24h": 164164551807.36288,
                "altcoin_volume_24h_reported": 983054318151.2336,
                "altcoin_market_cap": 924753281320.7476,
                "defi_volume_24h": 29323094889.041363,
                "defi_volume_24h_reported": 85311752794.61522,
                "defi_24h_percentage_change": 79.523575486318,
                "defi_market_cap": 55329213758.10103,
                "stablecoin_volume_24h": 300838412867.2987,
                "stablecoin_volume_24h_reported": 1666369625368.8372,
                "stablecoin_24h_percentage_change": 84.157196161854,
                "stablecoin_market_cap": 283193672220.0623,
                "derivatives_volume_24h": 2654454367650.1216,
                "derivatives_volume_24h_reported": 2723597883958.2993,
                "derivatives_24h_percentage_change": 82.290001191703,
                "total_market_cap_yesterday": 2473278129811.075,
                "total_volume_24h_yesterday": 165342300451.83,
                "total_market_cap_yesterday_percentage_change": -10.808799255799869,
                "total_volume_24h_yesterday_percentage_change": 85.46737660178476,
                "last_updated": "2026-02-06T01:31:59.999Z"
            }
        },
        "last_updated": "2026-02-06T01:31:59.999Z"
    }
}