{
    "status": {
        "timestamp": "2024-10-09T05:03:37.348Z",
        "error_code": 0,
        "error_message": null,
        "elapsed": 15,
        "credit_count": 1,
        "notice": null
    },
    "data": {
        "active_cryptocurrencies": 9873,
        "total_cryptocurrencies": 31642,
        "active_market_pairs": 86097,
        "active_exchanges": 752,
        "total_exchanges": 9369,
        "eth_dominance": 13.557828375541,
        "btc_dominance": 56.786814748938,
        "eth_dominance_yesterday": 13.45743119,
        "btc_dominance_yesterday": 56.82636762,
        "eth_dominance_24h_percentage_change": 0.100397185541,
        "btc_dominance_24h_percentage_change": -0.039552871062,
        "defi_volume_24h": 3652849916.5629954,
        "defi_volume_24h_reported": 24065961210.377663,
        "defi_market_cap": 60923105495.99015,
        "defi_24h_percentage_change": -8.4295996733,
        "stablecoin_volume_24h": 64248755830.89944,
        "stablecoin_volume_24h_reported": 370310941398.5924,
        "stablecoin_market_cap": 165583961377.75177,
        "stablecoin_24h_percentage_change": -9.861344382878,
        "derivatives_volume_24h": 666539061228.177,
        "derivatives_volume_24h_reported": 680070859618.2899,
        "derivatives_24h_percentage_change": -9.938302278777,
        "quote": {
            "USD": {
                "total_market_cap": 2171400908454.1067,
                "total_volume_24h": 69437602049.01,
                "total_volume_24h_reported": 381310026522.73,
                "altcoin_volume_24h": 41799011848.16631,
                "altcoin_volume_24h_reported": 236553564851.58047,
                "altcoin_market_cap": 938331497113.5111,
                "defi_volume_24h": 3652849916.5629954,
                "defi_volume_24h_reported": 24065961210.377663,
                "defi_24h_percentage_change": -8.4295996733,
                "defi_market_cap": 60923105495.99015,
                "stablecoin_volume_24h": 64248755830.89944,
                "stablecoin_volume_24h_reported": 370310941398.5924,
                "stablecoin_24h_percentage_change": -9.861344382878,
                "stablecoin_market_cap": 165583961377.75177,
                "derivatives_volume_24h": 666539061228.177,
                "derivatives_volume_24h_reported": 680070859618.2899,
                "derivatives_24h_percentage_change": -9.938302278777,
                "total_market_cap_yesterday": 2180807620356.732,
                "total_volume_24h_yesterday": 78093548902.89,
                "total_market_cap_yesterday_percentage_change": -0.4313407480246383,
                "total_volume_24h_yesterday_percentage_change": -11.084074133503336,
                "last_updated": "2024-10-09T05:01:59.999Z"
            }
        },
        "last_updated": "2024-10-09T05:01:59.999Z"
    }
}