{
    "status": {
        "timestamp": "2025-11-08T22:03:13.253Z",
        "error_code": 0,
        "error_message": null,
        "elapsed": 27,
        "credit_count": 1,
        "notice": null
    },
    "data": {
        "active_cryptocurrencies": 9337,
        "total_cryptocurrencies": 36488,
        "active_market_pairs": 116656,
        "active_exchanges": 889,
        "total_exchanges": 11413,
        "eth_dominance": 11.942960865666,
        "btc_dominance": 59.276230395173,
        "eth_dominance_yesterday": 11.96023881,
        "btc_dominance_yesterday": 59.18915884,
        "eth_dominance_24h_percentage_change": -0.017277944334,
        "btc_dominance_24h_percentage_change": 0.087071555173,
        "defi_volume_24h": 20248781012.01115,
        "defi_volume_24h_reported": 61342689073.914024,
        "defi_market_cap": 91349402991.59366,
        "defi_24h_percentage_change": -17.884783672611,
        "stablecoin_volume_24h": 123354754287.69724,
        "stablecoin_volume_24h_reported": 566560499473.6527,
        "stablecoin_market_cap": 282319188894.9589,
        "stablecoin_24h_percentage_change": -38.031043907056,
        "derivatives_volume_24h": 1101433291841.3103,
        "derivatives_volume_24h_reported": 1101433291841.3103,
        "derivatives_24h_percentage_change": -35.532628136339,
        "total_crypto_dex_currencies": 26797106,
        "today_incremental_crypto_number": 3,
        "past_24h_incremental_crypto_number": 46012,
        "past_7d_incremental_crypto_number": 348210,
        "past_30d_incremental_crypto_number": 1695556,
        "today_change_percent": 7.463493e-06,
        "tracked_yearly_number": {
            "maxIncrementalNumber": 1305553,
            "minIncrementalNumber": 3,
            "maxIncrementalDate": "2025-07-08T00:00:00.000Z",
            "minIncrementalDate": "2025-11-08T00:00:00.000Z"
        },
        "quote": {
            "USD": {
                "total_market_cap": 3440321396188.1675,
                "total_volume_24h": 145942182170.82,
                "total_volume_24h_reported": 597657739550.09,
                "altcoin_volume_24h": 91843268326.79521,
                "altcoin_volume_24h_reported": 427921731470.8542,
                "altcoin_market_cap": 1401028559049.231,
                "defi_volume_24h": 20248781012.01115,
                "defi_volume_24h_reported": 61342689073.914024,
                "defi_24h_percentage_change": -17.884783672611,
                "defi_market_cap": 91349402991.59366,
                "stablecoin_volume_24h": 123354754287.69724,
                "stablecoin_volume_24h_reported": 566560499473.6527,
                "stablecoin_24h_percentage_change": -38.031043907056,
                "stablecoin_market_cap": 282319188894.9589,
                "derivatives_volume_24h": 1101433291841.3103,
                "derivatives_volume_24h_reported": 1101433291841.3103,
                "derivatives_24h_percentage_change": -35.532628136339,
                "total_market_cap_yesterday": 3498036231640.2295,
                "total_volume_24h_yesterday": 222873459784.63,
                "total_market_cap_yesterday_percentage_change": -1.6499210308350598,
                "total_volume_24h_yesterday_percentage_change": -34.51791778534387,
                "last_updated": "2025-11-08T22:01:59.999Z"
            }
        },
        "last_updated": "2025-11-08T22:01:59.999Z"
    }
}