{
    "status": {
        "timestamp": "2026-03-28T00:21:49.228Z",
        "error_code": 0,
        "error_message": null,
        "elapsed": 20,
        "credit_count": 1,
        "notice": null
    },
    "data": {
        "active_cryptocurrencies": 8574,
        "total_cryptocurrencies": 37336,
        "active_market_pairs": 116470,
        "active_exchanges": 932,
        "total_exchanges": 11978,
        "eth_dominance": 10.486674539651,
        "btc_dominance": 57.926210817913,
        "eth_dominance_yesterday": 10.55004216,
        "btc_dominance_yesterday": 58.32890674,
        "eth_dominance_24h_percentage_change": -0.063367620349,
        "btc_dominance_24h_percentage_change": -0.402695922087,
        "defi_volume_24h": 8849077125.75283,
        "defi_volume_24h_reported": 31716708070.922962,
        "defi_market_cap": 57146218660.31129,
        "defi_24h_percentage_change": -6.498669021541,
        "stablecoin_volume_24h": 100476198695.10928,
        "stablecoin_volume_24h_reported": 499371199135.46765,
        "stablecoin_market_cap": 288584835198.14166,
        "stablecoin_24h_percentage_change": 8.586358775837,
        "derivatives_volume_24h": 756330354599.9874,
        "derivatives_volume_24h_reported": 789293749986.2778,
        "derivatives_24h_percentage_change": -2.033798459728,
        "total_crypto_dex_currencies": 47216252,
        "today_incremental_crypto_number": 0,
        "past_24h_incremental_crypto_number": 79371,
        "past_7d_incremental_crypto_number": 533355,
        "past_30d_incremental_crypto_number": 11430521,
        "today_change_percent": 2.3297068e-05,
        "tracked_yearly_number": {
            "maxIncrementalNumber": 7681147,
            "minIncrementalNumber": 12,
            "maxIncrementalDate": "2026-03-19T00:00:00.000Z",
            "minIncrementalDate": "2026-03-27T00:00:00.000Z"
        },
        "quote": {
            "USD": {
                "total_market_cap": 2290669984680.02,
                "total_volume_24h": 100344966592.28,
                "total_volume_24h_reported": 505434363245.09,
                "altcoin_volume_24h": 54196514596.25404,
                "altcoin_volume_24h_reported": 298276595518.7395,
                "altcoin_market_cap": 963771660211.6085,
                "defi_volume_24h": 8849077125.75283,
                "defi_volume_24h_reported": 31716708070.922962,
                "defi_24h_percentage_change": -6.498669021541,
                "defi_market_cap": 57146218660.31129,
                "stablecoin_volume_24h": 100476198695.10928,
                "stablecoin_volume_24h_reported": 499371199135.46765,
                "stablecoin_24h_percentage_change": 8.586358775837,
                "stablecoin_market_cap": 288584835198.14166,
                "derivatives_volume_24h": 756330354599.9874,
                "derivatives_volume_24h_reported": 789293749986.2778,
                "derivatives_24h_percentage_change": -2.033798459728,
                "total_market_cap_yesterday": 2361677774681.422,
                "total_volume_24h_yesterday": 93097898503.8,
                "total_market_cap_yesterday_percentage_change": -3.0066671568258414,
                "total_volume_24h_yesterday_percentage_change": 7.784351961697823,
                "last_updated": "2026-03-28T00:19:59.999Z"
            }
        },
        "last_updated": "2026-03-28T00:19:59.999Z"
    }
}