{
    "status": {
        "timestamp": "2024-10-03T01:30:10.998Z",
        "error_code": 0,
        "error_message": null,
        "elapsed": 62,
        "credit_count": 1,
        "notice": null
    },
    "data": {
        "active_cryptocurrencies": 9875,
        "total_cryptocurrencies": 31558,
        "active_market_pairs": 85016,
        "active_exchanges": 751,
        "total_exchanges": 9346,
        "eth_dominance": 13.508216424383,
        "btc_dominance": 56.768400963371,
        "eth_dominance_yesterday": 13.82578448,
        "btc_dominance_yesterday": 56.26758657,
        "eth_dominance_24h_percentage_change": -0.317568055617,
        "btc_dominance_24h_percentage_change": 0.500814393371,
        "defi_volume_24h": 5377637847.382193,
        "defi_volume_24h_reported": 31888949076.712143,
        "defi_market_cap": 60249534317.92464,
        "defi_24h_percentage_change": -13.619216938461,
        "stablecoin_volume_24h": 85424379717.22734,
        "stablecoin_volume_24h_reported": 499266896047.7262,
        "stablecoin_market_cap": 165697692029.1447,
        "stablecoin_24h_percentage_change": -19.604438064165,
        "derivatives_volume_24h": 835680199553.4363,
        "derivatives_volume_24h_reported": 850647100699.9994,
        "derivatives_24h_percentage_change": -17.435329936241,
        "quote": {
            "USD": {
                "total_market_cap": 2126415216304.1123,
                "total_volume_24h": 93253140228.59,
                "total_volume_24h_reported": 516176334364.89,
                "altcoin_volume_24h": 51949843211.84502,
                "altcoin_volume_24h_reported": 299515719210.7533,
                "altcoin_market_cap": 919283300166.4546,
                "defi_volume_24h": 5377637847.382193,
                "defi_volume_24h_reported": 31888949076.712143,
                "defi_24h_percentage_change": -13.619216938461,
                "defi_market_cap": 60249534317.92464,
                "stablecoin_volume_24h": 85424379717.22734,
                "stablecoin_volume_24h_reported": 499266896047.7262,
                "stablecoin_24h_percentage_change": -19.604438064165,
                "stablecoin_market_cap": 165697692029.1447,
                "derivatives_volume_24h": 835680199553.4363,
                "derivatives_volume_24h_reported": 850647100699.9994,
                "derivatives_24h_percentage_change": -17.435329936241,
                "total_market_cap_yesterday": 2155996819439.4778,
                "total_volume_24h_yesterday": 114888690337.2,
                "total_market_cap_yesterday_percentage_change": -1.3720615387111934,
                "total_volume_24h_yesterday_percentage_change": -18.83174927410988,
                "last_updated": "2024-10-03T01:27:59.999Z"
            }
        },
        "last_updated": "2024-10-03T01:27:59.999Z"
    }
}