{
    "status": {
        "timestamp": "2024-06-12T07:02:58.389Z",
        "error_code": 0,
        "error_message": null,
        "elapsed": 12,
        "credit_count": 1,
        "notice": null
    },
    "data": {
        "active_cryptocurrencies": 10076,
        "total_cryptocurrencies": 30189,
        "active_market_pairs": 82415,
        "active_exchanges": 781,
        "total_exchanges": 8682,
        "eth_dominance": 17.28164843763,
        "btc_dominance": 54.249414806885,
        "eth_dominance_yesterday": 17.30508609,
        "btc_dominance_yesterday": 54.24556204,
        "eth_dominance_24h_percentage_change": -0.02343765237,
        "btc_dominance_24h_percentage_change": 0.003852766885,
        "defi_volume_24h": 5852789648.156076,
        "defi_volume_24h_reported": 31030359007.774506,
        "defi_market_cap": 83188778044.20518,
        "defi_24h_percentage_change": -17.270669682152,
        "stablecoin_volume_24h": 76281168719.30914,
        "stablecoin_volume_24h_reported": 375261650827.44293,
        "stablecoin_market_cap": 155034981946.90668,
        "stablecoin_24h_percentage_change": -7.186891274443,
        "derivatives_volume_24h": 597430654776.9816,
        "derivatives_volume_24h_reported": 598529419764.0441,
        "derivatives_24h_percentage_change": 4.743910223529,
        "quote": {
            "USD": {
                "total_market_cap": 2444370340448.4595,
                "total_volume_24h": 82255298152.83,
                "total_volume_24h_reported": 390534728664.85,
                "altcoin_volume_24h": 51212198691.818436,
                "altcoin_volume_24h_reported": 236599516612.87317,
                "altcoin_market_cap": 1118313735042.1074,
                "defi_volume_24h": 5852789648.156076,
                "defi_volume_24h_reported": 31030359007.774506,
                "defi_24h_percentage_change": -17.270669682152,
                "defi_market_cap": 83188778044.20518,
                "stablecoin_volume_24h": 76281168719.30914,
                "stablecoin_volume_24h_reported": 375261650827.44293,
                "stablecoin_24h_percentage_change": -7.186891274443,
                "stablecoin_market_cap": 155034981946.90668,
                "derivatives_volume_24h": 597430654776.9816,
                "derivatives_volume_24h_reported": 598529419764.0441,
                "derivatives_24h_percentage_change": 4.743910223529,
                "total_market_cap_yesterday": 2456715440918.1396,
                "total_volume_24h_yesterday": 84517683115.32,
                "total_market_cap_yesterday_percentage_change": -0.5025042894290834,
                "total_volume_24h_yesterday_percentage_change": -2.6768184823560404,
                "last_updated": "2024-06-12T07:00:59.999Z"
            }
        },
        "last_updated": "2024-06-12T07:00:59.999Z"
    }
}