{
    "status": {
        "timestamp": "2026-04-11T07:22:37.497Z",
        "error_code": 0,
        "error_message": null,
        "elapsed": 23,
        "credit_count": 1,
        "notice": null
    },
    "data": {
        "active_cryptocurrencies": 8447,
        "total_cryptocurrencies": 37379,
        "active_market_pairs": 114716,
        "active_exchanges": 935,
        "total_exchanges": 12031,
        "eth_dominance": 10.948641345318,
        "btc_dominance": 59.130787071139,
        "eth_dominance_yesterday": 10.84925974,
        "btc_dominance_yesterday": 59.04394697,
        "eth_dominance_24h_percentage_change": 0.099381605318,
        "btc_dominance_24h_percentage_change": 0.086840101139,
        "defi_volume_24h": 9193491356.835249,
        "defi_volume_24h_reported": 33251310335.416428,
        "defi_market_cap": 59924139915.9833,
        "defi_24h_percentage_change": -8.419501048132,
        "stablecoin_volume_24h": 93694046948.5471,
        "stablecoin_volume_24h_reported": 435653688609.33374,
        "stablecoin_market_cap": 290064881921.9259,
        "stablecoin_24h_percentage_change": 0.751476413987,
        "derivatives_volume_24h": 621401170581.4016,
        "derivatives_volume_24h_reported": 664745178522.8557,
        "derivatives_24h_percentage_change": -17.048241432874,
        "total_crypto_dex_currencies": 48533734,
        "today_incremental_crypto_number": 0,
        "past_24h_incremental_crypto_number": 81229,
        "past_7d_incremental_crypto_number": 540680,
        "past_30d_incremental_crypto_number": 10808700,
        "today_change_percent": 1.2362537e-05,
        "tracked_yearly_number": {
            "maxIncrementalNumber": 7681147,
            "minIncrementalNumber": 7,
            "maxIncrementalDate": "2026-03-19T00:00:00.000Z",
            "minIncrementalDate": "2026-04-11T00:00:00.000Z"
        },
        "quote": {
            "USD": {
                "total_market_cap": 2463380597778.1836,
                "total_volume_24h": 95980887145.31,
                "total_volume_24h_reported": 443461909151.11,
                "altcoin_volume_24h": 60205652450.332825,
                "altcoin_volume_24h_reported": 282310689439.34845,
                "altcoin_market_cap": 1006764261754.2227,
                "defi_volume_24h": 9193491356.835249,
                "defi_volume_24h_reported": 33251310335.416428,
                "defi_24h_percentage_change": -8.419501048132,
                "defi_market_cap": 59924139915.9833,
                "stablecoin_volume_24h": 93694046948.5471,
                "stablecoin_volume_24h_reported": 435653688609.33374,
                "stablecoin_24h_percentage_change": 0.751476413987,
                "stablecoin_market_cap": 290064881921.9259,
                "derivatives_volume_24h": 621401170581.4016,
                "derivatives_volume_24h_reported": 664745178522.8557,
                "derivatives_24h_percentage_change": -17.048241432874,
                "total_market_cap_yesterday": 2432231107739.5547,
                "total_volume_24h_yesterday": 95567499615.59,
                "total_market_cap_yesterday_percentage_change": 1.2806961451775152,
                "total_volume_24h_yesterday_percentage_change": 0.4325607883253184,
                "last_updated": "2026-04-11T07:19:59.999Z"
            }
        },
        "last_updated": "2026-04-11T07:19:59.999Z"
    }
}