{
    "status": {
        "timestamp": "2026-02-12T19:23:22.603Z",
        "error_code": 0,
        "error_message": null,
        "elapsed": 41,
        "credit_count": 1,
        "notice": null
    },
    "data": {
        "active_cryptocurrencies": 8888,
        "total_cryptocurrencies": 37106,
        "active_market_pairs": 118612,
        "active_exchanges": 923,
        "total_exchanges": 11812,
        "eth_dominance": 10.285050557713,
        "btc_dominance": 58.119623654897,
        "eth_dominance_yesterday": 10.22003355,
        "btc_dominance_yesterday": 58.62965528,
        "eth_dominance_24h_percentage_change": 0.065017007713,
        "btc_dominance_24h_percentage_change": -0.510031625103,
        "defi_volume_24h": 11369934840.519403,
        "defi_volume_24h_reported": 37750039101.11327,
        "defi_market_cap": 55857190630.94183,
        "defi_24h_percentage_change": -3.102687020114,
        "stablecoin_volume_24h": 105896672990.64297,
        "stablecoin_volume_24h_reported": 558284185607.2515,
        "stablecoin_market_cap": 284577328222.32886,
        "stablecoin_24h_percentage_change": -4.424887168474,
        "derivatives_volume_24h": 907925441527.5206,
        "derivatives_volume_24h_reported": 936351881800.1775,
        "derivatives_24h_percentage_change": -13.632439392358,
        "total_crypto_dex_currencies": 33583220,
        "today_incremental_crypto_number": 0,
        "past_24h_incremental_crypto_number": 178413,
        "past_7d_incremental_crypto_number": 1079012,
        "past_30d_incremental_crypto_number": 3611239,
        "today_change_percent": 9.5285772e-05,
        "tracked_yearly_number": {
            "maxIncrementalNumber": 1305553,
            "minIncrementalNumber": 33,
            "maxIncrementalDate": "2025-07-08T00:00:00.000Z",
            "minIncrementalDate": "2026-02-12T00:00:00.000Z"
        },
        "quote": {
            "USD": {
                "total_market_cap": 2257272259440.438,
                "total_volume_24h": 104779396272.38,
                "total_volume_24h_reported": 564894443449.71,
                "altcoin_volume_24h": 59330223967.47829,
                "altcoin_volume_24h_reported": 342032741068.1273,
                "altcoin_market_cap": 945354117387.2571,
                "defi_volume_24h": 11369934840.519403,
                "defi_volume_24h_reported": 37750039101.11327,
                "defi_24h_percentage_change": -3.102687020114,
                "defi_market_cap": 55857190630.94183,
                "stablecoin_volume_24h": 105896672990.64297,
                "stablecoin_volume_24h_reported": 558284185607.2515,
                "stablecoin_24h_percentage_change": -4.424887168474,
                "stablecoin_market_cap": 284577328222.32886,
                "derivatives_volume_24h": 907925441527.5206,
                "derivatives_volume_24h_reported": 936351881800.1775,
                "derivatives_24h_percentage_change": -13.632439392358,
                "total_market_cap_yesterday": 2300522876026.4688,
                "total_volume_24h_yesterday": 110146028257.1,
                "total_market_cap_yesterday_percentage_change": -1.880034188607354,
                "total_volume_24h_yesterday_percentage_change": -4.872288242834628,
                "last_updated": "2026-02-12T19:21:59.999Z"
            }
        },
        "last_updated": "2026-02-12T19:21:59.999Z"
    }
}